emotions/__init__.py
emotions-1.2.7.dist-info/LICENSE.txt
emotions-1.2.7.dist-info/METADATA
emotions-1.2.7.dist-info/WHEEL
emotions-1.2.7.dist-info/top_level.txt
emotions-1.2.7.dist-info/RECORD
