Metadata-Version: 2.1
Name: emotions
Version: 1.2.7
Summary: This is a Program which can simulate EMOTIONS and MOOD.
Home-page: UNKNOWN
Author: Anurag Dutta
Author-email: mlmajumder4@gmail.com
License: UNKNOWN
Platform: UNKNOWN
Classifier: Programming Language :: Python :: 3
Classifier: License :: OSI Approved :: MIT License
Classifier: Operating System :: OS Independent
